{
  "NameConfig": {
    "last_name_set": [
      "Nguyen",
      "Ly",
      "Lam",
      "Kha",
      "Le"
    ],
    "middle_name_set": [
      "Trung",
      "Ngoc",
      "Thanh",
      "Hong",
      "Thanh"
    ],
    "first_name_set": [
      "Cuong",
      "Cong",
      "Han",
      "Mai",
      "Phuong"
    ]
  },

  "FieldConfig": {
    "field_name_set": [
      "Math",
      "Literature",
      "History",
      "English",
      "Geography",
      "Physic",
      "Chemistry"
    ]
  },

  "LevelConfig": {
    "level_name_set": [
      "10",
      "11",
      "12"
    ]
  }
}
